ml_wrappers/__init__.py
ml_wrappers/version.py
ml_wrappers/common/__init__.py
ml_wrappers/common/constants.py
ml_wrappers/common/gpu_kmeans.py
ml_wrappers/common/warnings_suppressor.py
ml_wrappers/dataset/__init__.py
ml_wrappers/dataset/dataset_utils.py
ml_wrappers/dataset/dataset_wrapper.py
ml_wrappers/dataset/timestamp_featurizer.py
ml_wrappers/model/__init__.py
ml_wrappers/model/base_wrapped_model.py
ml_wrappers/model/endpoint_wrapper.py
ml_wrappers/model/evaluator.py
ml_wrappers/model/fastai_wrapper.py
ml_wrappers/model/function_wrapper.py
ml_wrappers/model/image_model_wrapper.py
ml_wrappers/model/model_utils.py
ml_wrappers/model/model_wrapper.py
ml_wrappers/model/openai_wrapper.py
ml_wrappers/model/predictions_wrapper.py
ml_wrappers/model/pytorch_wrapper.py
ml_wrappers/model/tensorflow_wrapper.py
ml_wrappers/model/text_model_wrapper.py
ml_wrappers/model/wrapped_classification_model.py
ml_wrappers/model/wrapped_classification_without_proba_model.py
ml_wrappers/model/wrapped_regression_model.py
ml_wrappers-0.6.1.dist-info/licenses/LICENSE.txt
ml_wrappers-0.6.1.dist-info/METADATA
ml_wrappers-0.6.1.dist-info/WHEEL
ml_wrappers-0.6.1.dist-info/top_level.txt
ml_wrappers-0.6.1.dist-info/RECORD
